zt_proxy_integrations/__init__.py
zt_proxy_integrations/apigee/revert.py
zt_proxy_integrations/apigee/sync.py
zt_proxy_integrations/aws/revert.py
zt_proxy_integrations/aws/sync.py
zt_proxy_integrations/azure/revert.py
zt_proxy_integrations/azure/sync.py
zt_proxy_integrations/kong/revert.py
zt_proxy_integrations/kong/sync.py
zt_proxy_integrations/nginx/revert.py
zt_proxy_integrations/nginx/sync.py
zt_proxy_integrations/web_sync.py
zt_proxy_integrations-0.1.3.dist-info/entry_points.txt
zt_proxy_integrations-0.1.3.dist-info/METADATA
zt_proxy_integrations-0.1.3.dist-info/WHEEL
zt_proxy_integrations-0.1.3.dist-info/RECORD
