Metadata-Version: 2.3
Name: zt-proxy-integrations
Version: 0.1.3
Summary: Integrations for proxy sync and revert operations (apigee, aws, azure, kong, nginx)
Author: Your Name
Author-email: your.email@example.com
Requires-Python: >=3.12,<3.13
Classifier: Programming Language :: Python :: 3
Classifier: Programming Language :: Python :: 3.12
Requires-Dist: azure-identity (>=1.24.0,<2.0.0)
Requires-Dist: azure-mgmt-apimanagement (>=5.0.0,<6.0.0)
Requires-Dist: boto3 (>=1.40.20,<2.0.0)
Requires-Dist: flask (>=3.1.2,<4.0.0)
